{"payload":{"effective_from_utc":"2026-07-12T23:30:00Z","effective_time_basis":"reviewed_retrospective","effective_until_utc":"2026-07-15T01:32:55Z","limitations":["The market REST record was retrieved after settlement; effective-time coverage is a reviewed retrospective conclusion, not a contemporaneous metadata snapshot.","The retained series record identifies the official contract-terms and certification URLs, but this initial reviewed package retains the market-specific rule text rather than the linked PDF bytes.","Fee type, multiplier, and rounding identity are retained for compatibility only; B1a does not calculate or apply fees.","The REST product sources do not expose the WebSocket market UUID, so that UUID remains capture-derived identity."],"product_terms_sha256":"11407deb56f2da191ad76059fd771ef246c92102b6d4a2289568dda0c4dcf31c","reviewed_at_utc":"2026-07-16T19:52:09Z","source_manifest_sha256":"9861e9806999dcafef864809edfd12e1e9f96aad80debb4ae81af54cdd39c9d4","status":"reviewed"},"payload_sha256":"9dbecd8b1e189502a564f2fedef0fb7a10abe3756902107a7675fd9dc1c8b836","schema":"pmm.product_terms_review.v1"}
